datawaza/__init__.py
datawaza/clean.py
datawaza/explore.py
datawaza/model.py
datawaza/tools.py
datawaza/data/cb_2018_us_county_5m.cpg
datawaza/data/cb_2018_us_county_5m.dbf
datawaza/data/cb_2018_us_county_5m.prj
datawaza/data/cb_2018_us_county_5m.shp
datawaza/data/cb_2018_us_county_5m.shp.ea.iso.xml
datawaza/data/cb_2018_us_county_5m.shp.iso.xml
datawaza/data/cb_2018_us_county_5m.shx
datawaza/data/mnist_28x28_ch1_x0.pt
datawaza/data/svhn_32x32_ch3_x0.pt
datawaza/data/svhn_32x32_ch3_xhat0.pt
datawaza-0.1.3.dist-info/LICENSE
datawaza-0.1.3.dist-info/METADATA
datawaza-0.1.3.dist-info/WHEEL
datawaza-0.1.3.dist-info/top_level.txt
datawaza-0.1.3.dist-info/RECORD
