Metadata-Version: 2.1
Name: datawaza
Version: 0.1.3
Summary: Datawaza is a collection of tools for data exploration, visualization, data cleaning, pipeline creation, model iteration, and evaluation.
Home-page: https://datawaza.com
Author: Jim Beno
Author-email: jim@jimbeno.net
Project-URL: Documentation, https://datawaza.com
Project-URL: Source, https://github.com/jbeno/datawaza
Keywords: data science,visualization,machine learning,data analysis
Classifier: Development Status :: 3 - Alpha
Classifier: Intended Audience :: Science/Research
Classifier: Intended Audience :: Developers
Classifier: Programming Language :: Python :: 3.9
Classifier: Programming Language :: Python :: 3.10
Classifier: Programming Language :: Python :: 3.11
Classifier: Programming Language :: Python :: 3.12
Classifier: Operating System :: OS Independent
Classifier: License :: OSI Approved :: GNU General Public License v3 (GPLv3)
Classifier: Natural Language :: English
Classifier: Topic :: Software Development :: Libraries :: Python Modules
Classifier: Topic :: Scientific/Engineering :: Visualization
Classifier: Topic :: Scientific/Engineering :: Information Analysis
Requires-Python: >=3.9, <3.13
License-File: LICENSE
Requires-Dist: pandas >=2.2.1
Requires-Dist: numpy >=1.26.2
Requires-Dist: matplotlib >=3.8.2
Requires-Dist: seaborn >=0.13.2
Requires-Dist: pytz >=2023.3
Requires-Dist: scikit-learn >=1.5.0
Requires-Dist: joblib >=1.3.2
Requires-Dist: setuptools >=69.1.1
Requires-Dist: typing >=3.7.4.3
Requires-Dist: scipy >=1.11.4
Requires-Dist: cartopy >=0.22.0
Requires-Dist: geopandas >=0.14.3
Requires-Dist: statsmodels >=0.14.1
Requires-Dist: plotly >=5.19.0
Requires-Dist: nbformat >=4.2.0
Requires-Dist: scikeras >=0.13.0
Requires-Dist: xgboost >=2.0.3
Requires-Dist: imbalanced-learn >=0.12.3
Requires-Dist: tensorflow >=2.16.1
Requires-Dist: keras >=3.2.0
Requires-Dist: torch >=2.1.0
Requires-Dist: importlib-resources >=6.3.2 ; python_version < "3.10"
Provides-Extra: doc
Requires-Dist: pydata-sphinx-theme ~=0.15.2 ; extra == 'doc'
Requires-Dist: sphinx-design ~=0.5.0 ; extra == 'doc'
Requires-Dist: Sphinx ~=7.2.6 ; extra == 'doc'
Requires-Dist: myst-parser ~=2.0.0 ; extra == 'doc'
Requires-Dist: sphinx-favicon ~=1.0.1 ; extra == 'doc'
Requires-Dist: nbsphinx ~=0.9.3 ; extra == 'doc'
Provides-Extra: test
Requires-Dist: pytest >=8.1.1 ; extra == 'test'
Requires-Dist: pytest-cov >=4.1.0 ; extra == 'test'
Requires-Dist: coverage >=6.5.0 ; extra == 'test'
Requires-Dist: coveralls >=3.3.1 ; extra == 'test'
